odoo/addons/sale_margin_delivery_cost/README.rst
odoo/addons/sale_margin_delivery_cost/__init__.py
odoo/addons/sale_margin_delivery_cost/__manifest__.py
odoo/addons/sale_margin_delivery_cost/i18n/es.po
odoo/addons/sale_margin_delivery_cost/i18n/it.po
odoo/addons/sale_margin_delivery_cost/i18n/sale_margin_delivery_cost.pot
odoo/addons/sale_margin_delivery_cost/models/__init__.py
odoo/addons/sale_margin_delivery_cost/models/delivery_carrier.py
odoo/addons/sale_margin_delivery_cost/models/sale_order.py
odoo/addons/sale_margin_delivery_cost/models/sale_order_other_cost.py
odoo/addons/sale_margin_delivery_cost/readme/CONFIGURATION.rst
odoo/addons/sale_margin_delivery_cost/readme/DESCRIPTION.rst
odoo/addons/sale_margin_delivery_cost/readme/USAGE.rst
odoo/addons/sale_margin_delivery_cost/security/ir.model.access.csv
odoo/addons/sale_margin_delivery_cost/static/description/icon.png
odoo/addons/sale_margin_delivery_cost/static/description/index.html
odoo/addons/sale_margin_delivery_cost/views/delivery_carrier.xml
odoo/addons/sale_margin_delivery_cost/views/sale_order.xml
odoo14_addon_sale_margin_delivery_cost-14.0.1.0.1.dev8.dist-info/METADATA
odoo14_addon_sale_margin_delivery_cost-14.0.1.0.1.dev8.dist-info/WHEEL
odoo14_addon_sale_margin_delivery_cost-14.0.1.0.1.dev8.dist-info/top_level.txt
odoo14_addon_sale_margin_delivery_cost-14.0.1.0.1.dev8.dist-info/RECORD
